{
    "spw":
    {
        "0": 0,
        "1": 3,
        "2": 2,
        "3": 3,
        "4": 3,
        "5": 2,
        "6": 3,
        "7": 3,
        "8": 3,
        "9": 4
    },
    "safeSpaces" : {
        "0": [
            [0, 0, 0, 0, 0, 0],
            [0, 0, 0, 0, 0, 0],
            [0, 0, 0, 0, 0, 0]
        ],
        "1": [
            [0, 0, 0, 0, 0, 0],
            [1, 0, 1, 0, 0, 0],
            [1, 0, 0, 0, 0, 0]
        ],
        "2": [
            [0, 1, 0, 1, 0, 0],
            [0, 0, 0, 0, 0, 0],
            [0, 0, 0, 0, 0, 0]
        ],
        "3": [
            [0, 0, 0, 0, 0, 0],
            [0, 0, 1, 0, 0, 0],
            [1, 0, 0, 1, 0, 0]
        ],
        "4": [
            [0, 1, 0, 0, 0, 1],
            [0, 0, 0, 0, 1, 0],
            [0, 0, 0, 0, 0, 0]
        ],
        "5": [
            [0, 0, 0, 0, 0, 0],
            [0, 0, 0, 0, 0, 0],
            [0, 0, 0, 1, 1, 0]
        ],
        "6": [
            [0, 0, 1, 0, 0, 0],
            [0, 0, 0, 0, 0, 1],
            [0, 1, 0, 0, 0, 0]
        ],
        "7": [
            [0, 0, 0, 0, 1, 1],
            [0, 0, 0, 0, 0, 0],
            [0, 0, 0, 0, 0, 1]
        ],
        "8": [
            [0, 0, 0, 0, 1, 1],
            [0, 0, 0, 0, 0, 0],
            [0, 0, 0, 1, 0, 0]
        ],
        "9": [
            [0, 0, 1, 0, 0, 1],
            [0, 0, 0, 0, 0, 1],
            [0, 0, 0, 0, 0, 1]
        ]
    },
    "maps":
    {
        "1": {
            "A": [
                ["IF", "PC", "FF", "SM", "B", "Jr"],
                ["SM", "IF", "PC", "B", "IF", "PC"],
                ["FF", "Jr", "IF", "PC", "FF", "FF"]
            ],
            "B": [
                ["Jr", "IF", "FF", "FF", "PC", "PC"],
                ["FF", "B", "PC", "SM", "IF", "Jr"],
                ["IF", "PC", "SM", "B", "FF", "IF"]
            ],
            "C": [
                ["Jr", "PC", "FF", "SM", "ST", "PC"],
                ["SM", "IF", "FF", "B", "IF", "ST"],
                ["FF", "Jr", "IF", "B", "FF", "IF"]
            ],
            "D": [
                ["PC", "PC", "IF", "FF", "B", "PC"],
                ["FF", "B", "FF", "SM", "IF", "Jr"],
                ["IF", "Jr", "SM", "PC", "FF", "IF"]
            ],
            "E": [
                ["IF", "IF", "FF", "FF", "PC", "Jr"],
                ["SM", "B", "FF", "B", "FF", "ST"],
                ["IF", "ST", "SM", "PC", "Jr", "IF"]
            ],
            "F": [
                ["PC", "IF", "IF", "SM", "B", "PC"],
                ["FF", "IF", "PC", "SM", "FF", "Jr"],
                ["FF", "PC", "IF", "B", "Jr", "FF"]
            ]
        },
        "2": {
            "A": [
                ["MM", "PC", "PC", "MM", "ST", "PC"],
                ["ST", "FF", "B", "IF", "MM", "Jr"],
                ["MM", "B", "FF", "Jr", "IF", "PC"]
            ],
            "B": [
                ["PC", "MM", "PC", "MM", "Jr", "PC"],
                ["B", "FF", "PC", "IF", "MM", "Jr"],
                ["IF", "FF", "FF", "MM", "B", "FF"]
            ],
            "C": [
                ["Jr", "PC", "FF", "FF", "PC", "PC"],
                ["MM", "IF", "PC", "IF", "MM", "MM"],
                ["MM", "B", "FF", "Jr", "B", "FF"]
            ],
            "D": [
                ["Jr", "MM", "FF", "FF", "PC", "B"],
                ["MM", "IF", "B", "IF", "Jr", "MM"],
                ["IF", "PC", "PC", "MM", "IF", "PC"]
            ],
            "E": [
                ["MM", "PC", "B", "IF", "ST", "PC"],
                ["B", "IF", "PC", "MM", "Jr", "Jr"],
                ["MM", "ST", "FF", "MM", "PC", "FF"]
            ],
            "F": [
                ["PC", "MM", "B", "IF", "Jr", "B"],
                ["MM", "FF", "PC", "IF", "MM", "MM"],
                ["IF", "PC", "PC", "Jr", "IF", "FF"]
            ]
        },
        "3": {
            "A": [
                ["Jr", "B", "B", "MM", "ST", "PS"],
                ["FF", "PS", "PS", "IF", "Jr", "MM"],
                ["IF", "PS", "PC", "PC", "ST", "FF"]
            ],
            "B": [
                ["IF", "MM", "B", "PS", "MM", "PS"],
                ["FF", "MM", "MM", "FF", "PS", "B"],
                ["PS", "Jr", "FF", "FF", "Jr", "IF"]
            ],
            "C": [
                ["ST", "B", "PS", "PC", "Jr", "PS"],
                ["MM", "MM", "PS", "FF", "Jr", "B"],
                ["IF", "PS", "PC", "FF", "ST", "IF"]
            ],
            "D": [
                ["IF", "MM", "PS", "PS", "MM", "IF"],
                ["IF", "B", "MM", "FF", "Jr", "B"],
                ["PS", "PS", "FF", "MM", "Jr", "IF"]
            ],
            "E": [
                ["Jr", "B", "B", "MM", "MM", "PS"],
                ["FF", "PS", "MM", "FF", "PS", "MM"],
                ["IF", "Jr", "FF", "FF", "PS", "IF"]
            ],
            "F": [
                ["IF", "MM", "B", "MM", "Jr", "IF"],
                ["IF", "MM", "PS", "IF", "PS", "B"],
                ["PS", "Jr", "FF", "MM", "PS", "FF"]
            ]
        },
        "4": {
            "A": [
                ["B", "PC", "FF", "PC", "Jr", "PS"],
                ["PC", "Jr", "IF", "MM", "PC", "IF"],
                ["B", "MM", "FF", "ST", "PS", "ST"]
            ],
            "B": [
                ["Jr", "PS", "PS", "PC", "Jr", "PS"],
                ["MM", "FF", "MM", "MM", "IF", "IF"],
                ["B", "B", "PC", "FF", "MM", "PS"]
            ],
            "C": [
                ["PS", "PC", "FF", "FF", "MM", "PS"],
                ["MM", "Jr", "MM", "B", "IF", "Jr"],
                ["PS", "MM", "PC", "IF", "PS", "B"]
            ],
            "D": [
                ["B", "PS", "FF", "PC", "MM", "PS"],
                ["MM", "Jr", "IF", "B", "PC", "Jr"],
                ["PS", "MM", "IF", "FF", "MM", "PS"]
            ],
            "E": [
                ["Jr", "PC", "PS", "PC", "ST", "PC"],
                ["PC", "FF", "MM", "B", "IF", "IF"],
                ["PS", "B", "FF", "Jr", "MM", "ST"]
            ],
            "F": [
                ["PS", "PS", "PS", "FF", "Jr", "PC"],
                ["MM", "FF", "MM", "MM", "PC", "IF"],
                ["PS", "B", "IF", "Jr", "MM", "B"]
            ]
        },
        "5": {
            "A": [
                ["IF", "PS", "FF", "IF", "ST", "IF"],
                ["PC", "B", "Jr", "ST", "B", "Jr"],
                ["IF", "PS", "PC", "FF", "MM", "MM"]
            ],
            "B": [
                ["IF", "PC", "FF", "MM", "B", "IF"],
                ["IF", "B", "Jr", "PS", "FF", "PC"],
                ["FF", "PS", "Jr", "IF", "MM", "FF"]
            ],
            "C": [
                ["IF", "MM", "FF", "MM", "PS", "PC"],
                ["IF", "B", "IF", "PS", "FF", "Jr"],
                ["FF", "B", "Jr", "PC", "IF", "FF"]
            ],
            "D": [
                ["B", "MM", "FF", "IF", "PS", "PC"],
                ["PC", "PC", "IF", "Jr", "B", "Jr"],
                ["IF", "PS", "PC", "FF", "IF", "MM"]
            ],
            "E": [
                ["B", "MM", "Jr", "IF", "PS", "PC"],
                ["IF", "ST", "IF", "ST", "FF", "Jr"],
                ["IF", "B", "MM", "PC", "PS", "FF"]
            ],
            "F": [
                ["B", "PC", "Jr", "MM", "B", "PC"],
                ["IF", "PC", "IF", "Jr", "FF", "PC"],
                ["FF", "ST", "PS", "MM", "PS", "IF"]
            ]
        },
        "6": {  
            "A": [
                ["B", "ST", "IF", "PS", "B", "FF"],
                ["FF", "ST", "FF", "Jr", "Jr", "FF"],
                ["MM", "IF", "PS", "B", "PC", "MM"]
            ],
            "B": [
                ["B", "Jr", "MM", "PC", "FF", "Jr"],
                ["MM", "FF", "FF", "IF", "FF", "PS"],
                ["MM", "IF", "PS", "B", "PC", "MM"]
            ],
            "C": [
                ["B", "Jr", "IF", "PS", "FF", "PS"],
                ["FF", "B", "IF", "IF", "Jr", "FF"],
                ["MM", "FF", "PS", "IF", "PS", "MM"]
            ],
            "D": [
                ["PS", "FF", "MM", "PC", "PS", "FF"],
                ["MM", "ST", "IF", "ST", "Jr", "PS"],
                ["IF", "FF", "B", "B", "FF", "JR"]
            ],
            "E": [
                ["PS", "FF", "MM", "PS", "B", "PC"],
                ["MM", "FF", "IF", "IF", "Jr", "FF"],
                ["IF", "IF", "PS", "PS", "FF", "Jr"]
            ],
            "F": [
                ["PC", "MM", "FF", "PC", "PS", "Jr"],
                ["MM", "B", "IF", "Jr", "FF", "PS"],
                ["MM", "FF", "B", "IF", "FF", "MM"]
            ]
        },
        "7": {
            "A": [
                ["PC", "FF", "ST", "MM", "IF", "Jr"],
                ["PC", "B", "Jr", "FF", "B", "IF"],
                ["FF", "IF", "MM", "ST", "PS", "PC"]
            ],
            "B": [
                ["IF", "Jr", "MM", "PS", "B", "IF"],
                ["FF", "B", "PC", "IF", "FF", "MM"],
                ["FF", "PC", "Jr", "ST", "PS", "IF"]
            ],
            "C": [
                ["PC", "Jr", "IF", "PS", "MM", "ST"],
                ["FF", "PC", "B", "IF", "MM", "PS"],
                ["Jr", "FF", "PC", "ST", "IF", "FF"]
            ],
            "D": [
                ["Jr", "FF", "PC", "B", "IF", "FF"],
                ["PC", "MM", "FF", "Jr", "ST", "PS"],
                ["IF", "Jr", "MM", "IF", "PS", "MM"]
            ],
            "E": [
                ["PS", "PC", "IF", "ST", "PS", "FF"],
                ["FF", "MM", "PS", "B", "IF", "PC"],
                ["IF", "FF", "ST", "MM", "IF", "PC"]
            ],
            "F": [
                ["MM", "Jr", "MM", "PC", "FF", "PS"],
                ["FF", "Jr", "B", "PS", "PC", "ST"],
                ["IF", "PC", "MM", "Jr", "ST", "IF"]
            ]
        },
        "8": {
            "A": [
                ["PC", "FF", "MM", "ST", "PS", "FF"],
                ["PC", "B", "PS", "MM", "PS", "IF"],
                ["FF", "IF", "IF", "PC", "PS", "Jr"]
            ],
            "B": [
                ["IF", "MM", "IF", "B", "PS", "IF"],
                ["FF", "IF", "MM", "PC", "Jr", "B"],
                ["PS", "PC", "PS", "ST", "MM", "FF"]
            ],
            "C": [
                ["Jr", "PS", "PC", "ST", "PS", "IF"],
                ["MM", "Jr", "IF", "MM", "PS", "B"],
                ["IF", "PC", "PS", "IF", "MM", "FF"]
            ],
            "D": [
                ["Jr", "MM", "IF", "PC", "B", "IF"],
                ["FF", "IF", "MM", "PC", "Jr", "ST"],
                ["FF", "PC", "Jr", "MM", "PS", "PS"]
            ],
            "E": [
                ["IF", "PS", "FF", "ST", "Jr", "PC"],
                ["MM", "PS", "IF", "Jr", "B", "MM"],
                ["IF", "Jr", "PS", "PC", "PS", "FF"]
            ],
            "F": [
                ["PS", "Jr", "IF", "Jr", "MM", "PC"],
                ["FF", "MM", "PC", "ST", "B", "PS"],
                ["IF", "MM", "PS", "PS", "FF", "IF"]
            ]
        },
        "9": {
            "A": [
                ["PC", "FF", "ST", "MM", "IF", "Jr"],
                ["PC", "B", "Jr", "FF", "B", "IF"],
                ["FF", "IF", "MM", "ST", "PS", "PC"]
            ],
            "B": [
                ["IF", "Jr", "MM", "PS", "B", "IF"],
                ["FF", "B", "PC", "IF", "FF", "MM"],
                ["FF", "PC", "Jr", "ST", "PS", "IF"]
            ],
            "C": [
                ["PC", "Jr", "IF", "PS", "MM", "ST"],
                ["FF", "PC", "B", "IF", "MM", "PS"],
                ["Jr", "FF", "PC", "ST", "IF", "FF"]
            ],
            "D": [
                ["Jr", "FF", "PC", "B", "IF", "FF"],
                ["PC", "MM", "FF", "Jr", "ST", "PS"],
                ["IF", "Jr", "MM", "IF", "PS", "MM"]
            ],
            "E": [
                ["PS", "PC", "IF", "ST", "PS", "FF"],
                ["FF", "MM", "PS", "B", "IF", "PC"],
                ["IF", "FF", "ST", "MM", "IF", "PC"]
            ],
            "F": [
                ["MM", "Jr", "MM", "PC", "FF", "PS"],
                ["FF", "Jr", "B", "PS", "PC", "ST"],
                ["IF", "PC", "MM", "Jr", "ST", "IF"]
            ]
        }
    }
}
